ogd/utils/__init__.py
ogd/utils/JOWILDER/__init__.py
ogd/utils/JOWILDER/jowilder_utils.py
ogd/utils/LAKELAND/__init__.py
ogd/utils/LAKELAND/get_stats.py
ogd/utils/LAKELAND/get_stats_feat.py
ogd/utils/LAKELAND/lakeland_utils.py
ogd/utils/VRTeX/activity.py
ogd/utils/VRTeX/preprocessing.py
ogd/utils/WAVES/__init__.py
ogd/utils/WAVES/waves_utils.py
ogd/utils/general/FeatureSetOptions.py
ogd/utils/general/Workflow.py
ogd/utils/general/__init__.py
ogd/utils/general/features.py
ogd/utils/general/general.py
OGDUtils-2.1.0.dist-info/LICENSE
OGDUtils-2.1.0.dist-info/METADATA
OGDUtils-2.1.0.dist-info/WHEEL
OGDUtils-2.1.0.dist-info/top_level.txt
OGDUtils-2.1.0.dist-info/RECORD
