Metadata-Version: 2.1
Name: OGDUtils
Version: 2.1.0
Summary: A package with utilities for working with output data from the Open Game Data core
Author: John McCloskey, Mia Xiao, Renee Li
Author-email: Luke Swanson <superscription58@gmail.com>
Project-URL: Homepage, https://github.com/opengamedata/OGDUtils
Project-URL: Bug Tracker, https://github.com/opengamedata/OGDUtils/issues
Classifier: Programming Language :: Python :: 3
Classifier: License :: OSI Approved :: MIT License
Classifier: Operating System :: OS Independent
Requires-Python: >=3.12
License-File: LICENSE
Requires-Dist: ipywidgets==8.0.*
Requires-Dist: numpy==2.1.*
Requires-Dist: pandas==2.2.*
Requires-Dist: scikit-learn==1.5.*
